README.md
setup.cfg
setup.py
reactivestreams/__init__.py
reactivestreams/publisher.py
reactivestreams/subscriber.py
reactivestreams/subscription.py
rsocket/__init__.py
rsocket/composite_metadata.py
rsocket/connection.py
rsocket/frame.py
rsocket/handlers.py
rsocket/payload.py
rsocket/rsocket.py
rsocket/timer.py
rsocket/wellknown_mimetype.py
rsockettest.egg-info/PKG-INFO
rsockettest.egg-info/SOURCES.txt
rsockettest.egg-info/dependency_links.txt
rsockettest.egg-info/top_level.txt
rsockettest.egg-info/zip-safe